dubbo_client/__init__.py
dubbo_client/common.py
dubbo_client/config.py
dubbo_client/registry.py
dubbo_client/rpcerror.py
dubbo_client/rpclib.py
tests/__init__.py
tests/test_config.py
tests/test_kstore_platform.py
tests/test_performance.py
tests/test_rawclient.py
tests/test_register_config.py
tests/test_registry.py
tests/test_rpclib.py
dubbo_python3-1.0.3.dist-info/AUTHORS.md
dubbo_python3-1.0.3.dist-info/LICENSE
dubbo_python3-1.0.3.dist-info/METADATA
dubbo_python3-1.0.3.dist-info/WHEEL
dubbo_python3-1.0.3.dist-info/top_level.txt
dubbo_python3-1.0.3.dist-info/RECORD
