Metadata-Version: 2.1
Name: dubbo-python3
Version: 1.0.3
Summary: Python3 Dubbo Client
Home-page: https://github.com/nickfan/dubbo-python3
Author: Nick Fan
Author-email: nickfan@gmail.com
License: UNKNOWN
Download-URL: https://github.com/nickfan/dubbo-python3/raw/master/dist/dubbo-python3-1.0.3-py3.6.egg
Keywords: Dubbo,JSON-RPC,JSON,RPC,Client,HTTP-Client,Remote Procedure Call,JavaScript Object Notation,
Platform: UNKNOWN
Classifier: Development Status :: 4 - Beta
Classifier: Environment :: Web Environment
Classifier: Intended Audience :: Developers
Classifier: License :: OSI Approved :: MIT License
Classifier: Operating System :: OS Independent
Classifier: Programming Language :: Python :: 2
Classifier: Topic :: Software Development :: Libraries :: Python Modules
Classifier: Topic :: Communications
Classifier: Topic :: System :: Networking
Classifier: Topic :: Internet :: WWW/HTTP
Classifier: Topic :: Internet :: WWW/HTTP :: HTTP Servers
Classifier: Topic :: Internet :: WWW/HTTP :: WSGI :: Application
Requires-Dist: kazoo (>=2.0.0)
Requires-Dist: jsonrpcclient (>=3.3.0)
